odoo/addons/mrp_tag/README.rst
odoo/addons/mrp_tag/__init__.py
odoo/addons/mrp_tag/__manifest__.py
odoo/addons/mrp_tag/i18n/it.po
odoo/addons/mrp_tag/i18n/mrp_tag.pot
odoo/addons/mrp_tag/models/__init__.py
odoo/addons/mrp_tag/models/mrp_production.py
odoo/addons/mrp_tag/models/mrp_tag.py
odoo/addons/mrp_tag/readme/CONTRIBUTORS.rst
odoo/addons/mrp_tag/readme/DESCRIPTION.rst
odoo/addons/mrp_tag/readme/USAGE.rst
odoo/addons/mrp_tag/security/ir.model.access.csv
odoo/addons/mrp_tag/static/description/icon.png
odoo/addons/mrp_tag/static/description/index.html
odoo/addons/mrp_tag/views/mrp_production_view.xml
odoo/addons/mrp_tag/views/mrp_tag_view.xml
odoo14_addon_mrp_tag-14.0.1.0.1.dist-info/METADATA
odoo14_addon_mrp_tag-14.0.1.0.1.dist-info/WHEEL
odoo14_addon_mrp_tag-14.0.1.0.1.dist-info/top_level.txt
odoo14_addon_mrp_tag-14.0.1.0.1.dist-info/RECORD
